rpvVoterIndex/__init__.py
rpvVoterIndex/rpvVoterIndex.py
rpvVoterIndex-0.2.0.dist-info/LICENSE.txt
rpvVoterIndex-0.2.0.dist-info/METADATA
rpvVoterIndex-0.2.0.dist-info/WHEEL
rpvVoterIndex-0.2.0.dist-info/top_level.txt
rpvVoterIndex-0.2.0.dist-info/RECORD
